__init__.py
microservice/__init__.py
microservice/exceptions.py
microservice/fastapi_middlewares.py
microservice/shared.py
microservice_NoLabs-1.0.0.dist-info/METADATA
microservice_NoLabs-1.0.0.dist-info/WHEEL
microservice_NoLabs-1.0.0.dist-info/top_level.txt
microservice_NoLabs-1.0.0.dist-info/RECORD
